{"type":2300,"data":{"Apellido":"Jorgeee","Incidentes":[{"Descripcion":"Discusin","idIncidente":3}],"Nombre":"Jorge","NroDocumento":1,"NroPlaca":null,"OrgDelictiva":null,"TipoDocumento":1,"_id":"Persona/165364","_key":"165364","_rev":"_XzLmLb---_"}}
{"type":2300,"data":{"Apellido":"Wayne","Incidentes":[],"Nombre":"Bruce","NroDocumento":2,"NroPlaca":null,"OrgDelictiva":null,"TipoDocumento":1,"_id":"Persona/165368","_key":"165368","_rev":"_XzLmLb---B"}}
{"type":2300,"data":{"Apellido":"Loco","Incidentes":[{"Descripcion":"Una Felona","idIncidente":2}],"Nombre":"Payaso","NroDocumento":3,"NroPlaca":null,"OrgDelictiva":1,"TipoDocumento":1,"_id":"Persona/165370","_key":"165370","_rev":"_XzLmLb---D"}}
{"type":2300,"data":{"Apellido":"Loco","Incidentes":[{"Descripcion":"Una Felona","idIncidente":2}],"Nombre":"Payaso2","NroDocumento":4,"NroPlaca":null,"OrgDelictiva":1,"TipoDocumento":1,"_id":"Persona/165372","_key":"165372","_rev":"_XzLmLb---F"}}
{"type":2300,"data":{"Apellido":"Guason","Incidentes":[{"Descripcion":"Una Felona","idIncidente":2}],"Nombre":"El","NroDocumento":5,"NroPlaca":null,"OrgDelictiva":1,"TipoDocumento":1,"_id":"Persona/165374","_key":"165374","_rev":"_XzLmLb---H"}}
{"type":2300,"data":{"Apellido":"Mask","Incidentes":[{"Descripcion":"Un Robo","idIncidente":1}],"Nombre":"Black","NroDocumento":6,"NroPlaca":null,"OrgDelictiva":2,"TipoDocumento":1,"_id":"Persona/165376","_key":"165376","_rev":"_XzLmLb---J"}}
{"type":2300,"data":{"Apellido":"Victima1","Incidentes":[{"Descripcion":"Un Robo","idIncidente":1}],"Nombre":"Marcelo","NroDocumento":7,"NroPlaca":null,"OrgDelictiva":null,"TipoDocumento":1,"_id":"Persona/165378","_key":"165378","_rev":"_XzLmLb---L"}}
{"type":2300,"data":{"Apellido":"Victima2","Incidentes":[{"Descripcion":"Una Felona","idIncidente":2},{"Descripcion":"Robo de propiedad de un ciudadano","idIncidente":4}],"Nombre":"Fernando","NroDocumento":8,"NroPlaca":null,"OrgDelictiva":null,"TipoDocumento":1,"_id":"Persona/165380","_key":"165380","_rev":"_XzLmLb---N"}}
{"type":2300,"data":{"Apellido":"Oficial1","Incidentes":[{"Descripcion":"Un Robo","idIncidente":1},{"Descripcion":"Robo de propiedad de un ciudadano","idIncidente":4}],"Nombre":"Alejandro","NroDocumento":9,"NroPlaca":1,"OrgDelictiva":null,"TipoDocumento":1,"_id":"Persona/165382","_key":"165382","_rev":"_XzLmLb---P"}}
{"type":2300,"data":{"Apellido":"Contacto1","Incidentes":[],"Nombre":"Vanesa","NroDocumento":10,"NroPlaca":null,"OrgDelictiva":null,"TipoDocumento":1,"_id":"Persona/165384","_key":"165384","_rev":"_XzLmLb---R"}}
{"type":2300,"data":{"Apellido":"Interno1","Incidentes":[{"Descripcion":"Un Robo","idIncidente":1},{"Descripcion":"Una Felona","idIncidente":2},{"Descripcion":"Discusin","idIncidente":3}],"Nombre":"Asunto","NroDocumento":11,"NroPlaca":2,"OrgDelictiva":null,"TipoDocumento":1,"_id":"Persona/165386","_key":"165386","_rev":"_XzLmLb---T"}}
{"type":2300,"data":{"Apellido":"Loco","Incidentes":[{"Descripcion":"Una Felonía","idIncidente":2}],"Nombre":"Payaso","NroDocumento":3,"NroPlaca":null,"OrgDelictiva":1,"TipoDocumento":1,"_id":"Persona/165370","_key":"165370","_rev":"_X0GYA3m--_"}}
{"type":2300,"data":{"Apellido":"Loco","Incidentes":[{"Descripcion":"Una Felonía","idIncidente":2}],"Nombre":"Payaso2","NroDocumento":4,"NroPlaca":null,"OrgDelictiva":1,"TipoDocumento":1,"_id":"Persona/165372","_key":"165372","_rev":"_X0GYQMK--_"}}
{"type":2300,"data":{"Apellido":"Guason","Incidentes":[{"Descripcion":"Una Felonía","idIncidente":2}],"Nombre":"El","NroDocumento":5,"NroPlaca":null,"OrgDelictiva":1,"TipoDocumento":1,"_id":"Persona/165374","_key":"165374","_rev":"_X0GYZfq--_"}}
{"type":2300,"data":{"Apellido":"Jorgeee","Incidentes":[{"Descripcion":"Discusión violenta","idIncidente":3}],"Nombre":"Jorge","NroDocumento":1,"NroPlaca":null,"OrgDelictiva":null,"TipoDocumento":1,"_id":"Persona/165364","_key":"165364","_rev":"_X0GY9_K--_"}}
{"type":2300,"data":{"Apellido":"Victima2","Incidentes":[{"Descripcion":"Una Felonía","idIncidente":2},{"Descripcion":"Robo de propiedad de un ciudadano","idIncidente":4}],"Nombre":"Fernando","NroDocumento":8,"NroPlaca":null,"OrgDelictiva":null,"TipoDocumento":1,"_id":"Persona/165380","_key":"165380","_rev":"_X0GZZpS--_"}}
{"type":2300,"data":{"Apellido":"Interno1","Incidentes":[{"Descripcion":"Un Robo","idIncidente":1},{"Descripcion":"Una Felonía","idIncidente":2},{"Descripcion":"Discusión violenta","idIncidente":3}],"Nombre":"Asunto","NroDocumento":11,"NroPlaca":2,"OrgDelictiva":null,"TipoDocumento":1,"_id":"Persona/165386","_key":"165386","_rev":"_X0GZ8wC--_"}}
